hdacpy/__init__.py
hdacpy/bip39_bip44_process.py
hdacpy/exceptions.py
hdacpy/transaction.py
hdacpy/type.py
hdacpy/typing.py
hdacpy/wallet.py
hdacpy-0.5.5.dist-info/DESCRIPTION.rst
hdacpy-0.5.5.dist-info/METADATA
hdacpy-0.5.5.dist-info/RECORD
hdacpy-0.5.5.dist-info/WHEEL
hdacpy-0.5.5.dist-info/metadata.json
hdacpy-0.5.5.dist-info/top_level.txt
